python_ms/__init__.py
python_ms/config.py
python_ms/ms.py
python_ms/py.typed
python_ms-1.1.1.dist-info/LICENSE
python_ms-1.1.1.dist-info/METADATA
python_ms-1.1.1.dist-info/WHEEL
python_ms-1.1.1.dist-info/RECORD
