Metadata-Version: 2.1
Name: python_ms
Version: 1.1.1
Summary: A Python equivalent to the JavaScript ms package.
Home-page: https://pypi.org/project/python-ms/
License: MIT
Keywords: package,python3,time
Author: Lari Liuhamo
Author-email: lari.liuhamo+pypi@gmail.com
Maintainer: Lari Liuhamo
Maintainer-email: lari.liuhamo+pypi@gmail.com
Requires-Python: >=3.10,<4.0
Classifier: Development Status :: 5 - Production/Stable
Classifier: Intended Audience :: Developers
Classifier: License :: OSI Approved :: MIT License
Classifier: Natural Language :: English
Classifier: Operating System :: OS Independent
Classifier: Programming Language :: Python :: 3
Classifier: Programming Language :: Python :: 3.10
Classifier: Programming Language :: Python :: 3.11
Classifier: Programming Language :: Python :: 3.12
Classifier: Programming Language :: Python :: 3.13
Classifier: Programming Language :: Python :: Implementation :: CPython
Classifier: Programming Language :: Python :: Implementation :: PyPy
Classifier: Topic :: Software Development :: Libraries
Classifier: Typing :: Typed
Project-URL: Changelog, https://github.com/Diapolo10/python-ms/blob/main/CHANGELOG.md
Project-URL: Documentation, https://github.com/Diapolo10/python-ms/tree/main/docs
Project-URL: Repository, https://github.com/Diapolo10/python-ms
Project-URL: Tracker, https://github.com/Diapolo10/python-ms/issues
